{
  "project_info": {
    "project_number": "759993335009",
    "project_id": "stations-map-app",
    "storage_bucket": "stations-map-app.appspot.com"
  },
  "client": [
    {
      "client_info": {
        "mobilesdk_app_id": "1:759993335009:android:22b1de23eef75d770bcba0",
        "android_client_info": {
          "package_name": "com.extrawest.flutter_map_training"
        }
      },
      "oauth_client": [
        {
          "client_id": "759993335009-0k96s63he281dj141s0vmju955j3oj3s.apps.googleusercontent.com",
          "client_type": 3
        }
      ],
      "api_key": [
        {
          "current_key": "AIzaSyDXwD-6kukVASbwlD3LPGyeZ3VdY6OHeuM"
        }
      ],
      "services": {
        "appinvite_service": {
          "other_platform_oauth_client": [
            {
              "client_id": "759993335009-0k96s63he281dj141s0vmju955j3oj3s.apps.googleusercontent.com",
              "client_type": 3
            },
            {
              "client_id": "759993335009-qnrvj0naqftij8dnohju3j1olfivdtuu.apps.googleusercontent.com",
              "client_type": 2,
              "ios_info": {
                "bundle_id": "com.extrawest.flutterMapTraining"
              }
            }
          ]
        }
      }
    }
  ],
  "configuration_version": "1"
}